artefact/__init__.py
artefact/assets/images/first_page_ava2.jpg
artefact/service/admin_delete_from_storage.py
artefact/service/api_openfda_service.py
artefact/service/authentication.py
artefact/service/database.py
artefact/service/documents_page_service.py
artefact/service/notifications.py
artefact/ui/gui/components/navigation.py
artefact/ui/gui/components/page_header.py
artefact/ui/gui/documents_page.py
artefact/ui/gui/first_page.py
artefact/ui/gui/forgot_password_page.py
artefact/ui/gui/login_page.py
artefact/ui/gui/main_page.py
artefact/ui/gui/medication_check_page.py
artefact/ui/gui/settings_page.py
artefact/ui/gui/sign_up_page.py
artefact/utils/constants.py
artefact/utils/traits.py
artefact/utils/validation.py
medbook_medical_hub-0.2.1.dist-info/METADATA
medbook_medical_hub-0.2.1.dist-info/WHEEL
medbook_medical_hub-0.2.1.dist-info/entry_points.txt
medbook_medical_hub-0.2.1.dist-info/licenses/LICENSE
medbook_medical_hub-0.2.1.dist-info/RECORD
