Metadata-Version: 2.4
Name: medbook-medical-hub
Version: 0.2.1
Summary: A desktop application that helps users manage medications and personal health records. Features include a monthly calendar with daily reminders, medical document storage, personalized pill risk monitoring, and personal profile editing
License-Expression: CC-BY-NC-4.0
License-File: LICENSE
Keywords: medication,scheduler,reminder,medical records,calendar,health,flet,firebase,desktop
Author: Anastasiia Bakhmutova
Author-email: bakhmutovaaa@gmail.com
Requires-Python: >=3.12,<4.0
Classifier: Programming Language :: Python :: 3
Classifier: Programming Language :: Python :: 3.12
Requires-Dist: firebase-admin (==6.6.0)
Requires-Dist: flet (==0.25.2)
Requires-Dist: pyrebase4 (==4.8.0)
Requires-Dist: setuptools (>=80.9.0,<81.0.0)
Project-URL: Homepage, https://github.com/unibo-dtm-se-2324-MedBook
Project-URL: Repository, https://github.com/unibo-dtm-se-2324-MedBook/artifact
